src/__init__.py
src/auth.py
src/category.py
src/env.py
src/image.py
src/markdown.py
src/tistory.py
local_first_tistory-0.0.2.dist-info/METADATA
local_first_tistory-0.0.2.dist-info/WHEEL
local_first_tistory-0.0.2.dist-info/entry_points.txt
local_first_tistory-0.0.2.dist-info/top_level.txt
local_first_tistory-0.0.2.dist-info/RECORD
