Metadata-Version: 2.1
Name: local-first-tistory
Version: 0.0.2
Summary: It will help you to manage locally saved markdown             to upload to Tistory
Home-page: https://github.com/choikangjae/local-first-tistory
Author: Kangjae Choi
Author-email: choikj33@gmail.com
License: MIT
Keywords: tistory terminal markdown image
Classifier: Operating System :: POSIX
Classifier: Natural Language :: English
Classifier: Programming Language :: Python :: 3
Classifier: Programming Language :: Python :: 3.9
Classifier: Topic :: Utilities
Classifier: Topic :: Terminals
Classifier: License :: OSI Approved :: MIT License
Requires-Dist: Markdown
Requires-Dist: python-dotenv
Requires-Dist: Requests
Requires-Dist: mdx-truly-sane-lists
Requires-Dist: markdown-link-attr-modifier
Requires-Dist: click
